pybenjarvis/__init__.py
pybenjarvis/__main__.py
pybenjarvis/install.py
pybenjarvis-3.0.1.dist-info/METADATA
pybenjarvis-3.0.1.dist-info/WHEEL
pybenjarvis-3.0.1.dist-info/top_level.txt
pybenjarvis-3.0.1.dist-info/RECORD
