Metadata-Version: 2.4
Name: pybenjarvis
Version: 3.0.1
Summary: PyBEN jarvis is a getter for Akamai auto_etp local repo. Also adds the 'jarvis' module to site-packages
Author: Ben Moskovitch
Author-email: Ben Moskovitch <darkflameben@gmail.com>
Maintainer-email: Ben Moskovitch <darkflameben@gmail.com>
Project-URL: Homepage, https://github.com/DarkFlameBEN/pybenjarvis.git
Keywords: python,gui,utils,utilities,automation,automation-tools
Classifier: Development Status :: 5 - Production/Stable
Classifier: Intended Audience :: Developers
Classifier: Topic :: Software Development :: Libraries
Classifier: Operating System :: OS Independent
Classifier: Programming Language :: Python :: 3.7
Classifier: Programming Language :: Python :: 3.8
Classifier: Programming Language :: Python :: 3.9
Classifier: Programming Language :: Python :: 3.10
Classifier: Programming Language :: Python :: 3.11
Classifier: Programming Language :: Python :: 3.12
Classifier: Programming Language :: Python :: 3.13
Requires-Python: >=3.8
Requires-Dist: pybenutils>=7.6.0
